{
  "id": "eri-code-009-retry-java-resilience4j",
  "name": "ERI-009: Retry - Java/Spring Boot with Resilience4j",
  "description": "Reference implementation of Retry pattern in Java/Spring Boot using Resilience4j, including backoff strategies and when to use/avoid retries.",
  "type": "local",
  "path": "./knowledge/ERIs/eri-code-009-retry-java-resilience4j/",
  "mode": "selectable",
  "tags": ["eri", "java", "spring-boot", "resilience4j", "retry", "fault-tolerance", "microservices"],
  "fetchHint": "Read ERI.md Overview and guidance (When to use/NOT use) before applying templates via mod-002."
}
